LICENSE
MANIFEST.in
README.md
package.json
setup.py
dash_dataflow_components/DataFlow.py
dash_dataflow_components/__init__.py
dash_dataflow_components/_imports_.py
dash_dataflow_components/dash_dataflow_components.min.js
dash_dataflow_components/dash_dataflow_components.min.js.map
dash_dataflow_components/interact.py
dash_dataflow_components/metadata.json
dash_dataflow_components/package-info.json
dash_dataflow_components.egg-info/PKG-INFO
dash_dataflow_components.egg-info/SOURCES.txt
dash_dataflow_components.egg-info/dependency_links.txt
dash_dataflow_components.egg-info/top_level.txt