Metadata-Version: 1.1
Name: dash-dataflow-components
Version: 0.0.8
Summary: Components that create easy to use editable dataflows.
Home-page: UNKNOWN
Author: Viktor Krückl <viktor@krueckl.de>
Author-email: UNKNOWN
License: MIT
Platform: UNKNOWN
Classifier: Framework :: Dash
